yahoo_ff/__init__.py
yahoo_ff/constants.py
yahoo_ff/database.py
yahoo_ff/tools.py
yahoo_ff/yahoo_ff.py
yahoo_ff-0.13.dist-info/DESCRIPTION.rst
yahoo_ff-0.13.dist-info/METADATA
yahoo_ff-0.13.dist-info/RECORD
yahoo_ff-0.13.dist-info/WHEEL
yahoo_ff-0.13.dist-info/metadata.json
yahoo_ff-0.13.dist-info/top_level.txt
