Metadata-Version: 2.0
Name: yahoo-ff
Version: 0.13
Summary: retrieve financial fundamental data for stocks
Home-page: http://github.com/alexandresobolevski/yahoo_ff
Author: Alexandre Sobolevski
Author-email: UNKNOWN
License: MIT
Platform: UNKNOWN
